setup.py
rtjp/__init__.py
rtjp/concurrence.py
rtjp/core.py
rtjp/errors.py
rtjp/eventlet.py
rtjp.egg-info/PKG-INFO
rtjp.egg-info/SOURCES.txt
rtjp.egg-info/dependency_links.txt
rtjp.egg-info/not-zip-safe
rtjp.egg-info/top_level.txt